moesif-aiohttp/__init__.py
moesif-aiohttp/event_mapper.py
moesif-aiohttp/logger_helper.py
moesif-aiohttp/middleware.py
moesif_aiohttp/__init__.py
moesif_aiohttp/event_mapper.py
moesif_aiohttp/logger_helper.py
moesif_aiohttp/middleware.py
moesif_aiohttp-1.1.0.dist-info/LICENSE
moesif_aiohttp-1.1.0.dist-info/METADATA
moesif_aiohttp-1.1.0.dist-info/WHEEL
moesif_aiohttp-1.1.0.dist-info/top_level.txt
moesif_aiohttp-1.1.0.dist-info/RECORD
