Metadata-Version: 2.1
Name: moesif-aiohttp
Version: 1.1.0
Summary: Moesif Middleware for AIOHTTP
Home-page: https://www.moesif.com/docs/server-integration/python-aiohttp/
Author: Moesif, Inc
License: Apache Software License
Keywords: log analysis restful api development debug wsgi flask bottle http middleware
Classifier: Development Status :: 4 - Beta
Classifier: Intended Audience :: Developers
Classifier: Topic :: Internet :: Log Analysis
Classifier: Topic :: Software Development :: Debuggers
Classifier: Topic :: Software Development :: Libraries
Classifier: Topic :: Internet :: WWW/HTTP
Classifier: License :: OSI Approved :: Apache Software License
Classifier: Programming Language :: Python :: 3.6
Classifier: Programming Language :: Python :: 3.7
Classifier: Programming Language :: Python :: 3.8
Classifier: Programming Language :: Python :: 3.9
Classifier: Programming Language :: Python :: 3.10
Classifier: Programming Language :: Python :: 3.11
License-File: LICENSE
Requires-Dist: moesifapi (>=1.4.5)
Requires-Dist: aiohttp (>=3.8.3)
Requires-Dist: aiohttp-sse (>=2.1.0)
Requires-Dist: aiohttp-sse-client2 (>=0.3.0)
Requires-Dist: asyncio (>=3.4.3)
Requires-Dist: gunicorn (>=20.1.0)
Requires-Dist: readerwriterlock (>=1.0.9)
Provides-Extra: dev
Provides-Extra: test
Requires-Dist: nose ; extra == 'test'
